snowpark_session/__init__.py
snowpark_session-0.1.2.dist-info/LICENSE
snowpark_session-0.1.2.dist-info/METADATA
snowpark_session-0.1.2.dist-info/WHEEL
snowpark_session-0.1.2.dist-info/entry_points.txt
snowpark_session-0.1.2.dist-info/RECORD
