Metadata-Version: 2.1
Name: snowpark-session
Version: 0.1.2
Summary: 
Author: Carlos D. Escobar-Valbuena
Author-email: carlosdavidescobar@gmail.com
Requires-Python: >=3.8,<4.0
Classifier: Programming Language :: Python :: 3
Classifier: Programming Language :: Python :: 3.8
Classifier: Programming Language :: Python :: 3.9
Classifier: Programming Language :: Python :: 3.10
Classifier: Programming Language :: Python :: 3.11
Classifier: Programming Language :: Python :: 3.12
Requires-Dist: azure-ai-ml (>=1.8.0,<2.0.0)
Requires-Dist: azureml-mlflow (>=1.52.0,<2.0.0)
Requires-Dist: snowflake-snowpark-python (==1.5.1) ; python_version >= "3.6" and python_version < "3.10"
